ntnx_microseg_py_client/__init__.py
ntnx_microseg_py_client/api_client.py
ntnx_microseg_py_client/api_response.py
ntnx_microseg_py_client/configuration.py
ntnx_microseg_py_client/custom_retry.py
ntnx_microseg_py_client/rest.py
ntnx_microseg_py_client/api/__init__.py
ntnx_microseg_py_client/api/address_groups_api.py
ntnx_microseg_py_client/api/directory_server_configs_api.py
ntnx_microseg_py_client/api/entity_groups_api.py
ntnx_microseg_py_client/api/network_security_policies_api.py
ntnx_microseg_py_client/api/service_groups_api.py
ntnx_microseg_py_client/models/__init__.py
ntnx_microseg_py_client/models/OneOfcommon/__init__.py
ntnx_microseg_py_client/models/OneOfcommon/v1/__init__.py
ntnx_microseg_py_client/models/OneOfcommon/v1/config/KVPairvalue.py
ntnx_microseg_py_client/models/OneOfcommon/v1/config/__init__.py
ntnx_microseg_py_client/models/OneOfmicroseg/__init__.py
ntnx_microseg_py_client/models/OneOfmicroseg/v4/__init__.py
ntnx_microseg_py_client/models/OneOfmicroseg/v4/config/CreateAddressGroupApiResponsedata.py
ntnx_microseg_py_client/models/OneOfmicroseg/v4/config/CreateDirectoryServerConfigApiResponsedata.py
ntnx_microseg_py_client/models/OneOfmicroseg/v4/config/CreateDsCategoryMappingApiResponsedata.py
ntnx_microseg_py_client/models/OneOfmicroseg/v4/config/CreateEntityGroupApiResponsedata.py
ntnx_microseg_py_client/models/OneOfmicroseg/v4/config/CreateNetworkSecurityPolicyApiResponsedata.py
ntnx_microseg_py_client/models/OneOfmicroseg/v4/config/CreateNetworkSecurityPolicyExportApiResponsedata.py
ntnx_microseg_py_client/models/OneOfmicroseg/v4/config/CreateNetworkSecurityPolicyImportApiResponsedata.py
ntnx_microseg_py_client/models/OneOfmicroseg/v4/config/CreateServiceGroupApiResponsedata.py
ntnx_microseg_py_client/models/OneOfmicroseg/v4/config/DeleteAddressGroupApiResponsedata.py
ntnx_microseg_py_client/models/OneOfmicroseg/v4/config/DeleteDirectoryServerConfigApiResponsedata.py
ntnx_microseg_py_client-4.2.1.dist-info/LICENSE.txt
ntnx_microseg_py_client-4.2.1.dist-info/METADATA
ntnx_microseg_py_client-4.2.1.dist-info/WHEEL
ntnx_microseg_py_client-4.2.1.dist-info/top_level.txt
ntnx_microseg_py_client-4.2.1.dist-info/RECORD
