Metadata-Version: 2.1
Name: ntnx-microseg-py-client
Version: 4.2.1
Summary: Nutanix Flow Management APIs
Home-page: 
Author-email: sdk@nutanix.com
Keywords: Nutanix,v4,SDK,Nutanix Flow Management APIs
License-File: LICENSE.txt
Requires-Dist: urllib3 ~=1.26
Requires-Dist: six ~=1.16
Requires-Dist: certifi <=2025.4.26,>=2024.7.4
Requires-Dist: python-dateutil ~=2.8
Requires-Dist: pysocks ~=1.7
